pyKevo/__init__.py
pyKevo/pyKevo.py
pyKevo-1.0.0.dist-info/DESCRIPTION.rst
pyKevo-1.0.0.dist-info/METADATA
pyKevo-1.0.0.dist-info/RECORD
pyKevo-1.0.0.dist-info/WHEEL
pyKevo-1.0.0.dist-info/entry_points.txt
pyKevo-1.0.0.dist-info/metadata.json
pyKevo-1.0.0.dist-info/top_level.txt
