Metadata-Version: 2.0
Name: pyKevo
Version: 1.0.0
Summary: A simple Python project for people with Kevo smartlocks.
Home-page: https://github.com/jeremyforan/pyKevo
Author: Jeremy Foran
Author-email: jeremy.foran@gmail.com
License: Creative Commons Attribution-ShareAlike 3.0
Keywords: Kevo Smartlock Smartlocks
Platform: UNKNOWN
Classifier: Intended Audience :: Developers
Classifier: Topic :: Home Automation
Classifier: License :: OSI Approved :: MIT License
Classifier: Programming Language :: Python :: 2
Classifier: Programming Language :: Python :: 2.6
Classifier: Programming Language :: Python :: 2.7
Classifier: Programming Language :: Python :: 3
Classifier: Programming Language :: Python :: 3.3
Classifier: Programming Language :: Python :: 3.4
Classifier: Programming Language :: Python :: 3.5
Requires-Dist: requests
